{
  "timestamp": "2026-01-06T11:22:59.556935",
  "source_file": "uploads/a8a41a1d-353c-4243-8e6c-fe70bb6322b4_numeralIntegration.c",
  "baseline": {
    "-O1": 0.006262063980102539,
    "-O2": 0.0033135414123535156,
    "-O3": 0.0033829212188720703
  },
  "AutoFlag": {
    "best_time": 0.002555370330810547,
    "total_evaluations": 2770,
    "enabled_flags": [
      "-faggressive-loop-optimizations",
      "-falign-labels",
      "-falign-loops",
      "-fassociative-math",
      "-fauto-inc-dec",
      "-fbranch-probabilities",
      "-fcaller-saves",
      "-fcode-hoisting",
      "-fcombine-stack-adjustments",
      "-fcommon",
      "-fcompare-elim",
      "-fcrossjumping",
      "-fcx-fortran-rules",
      "-fcx-limited-range",
      "-fdelayed-branch",
      "-fdse",
      "-fearly-inlining",
      "-ffinite-math-only",
      "-fipa-icf",
      "-finline-functions",
      "-fipa-pure-const",
      "-fipa-sra",
      "-fjump-tables",
      "-free",
      "-frename-registers",
      "-frerun-cse-after-loop",
      "-fsched-interblock",
      "-fsched-spec",
      "-fsection-anchors",
      "-fshrink-wrap",
      "-fsplit-paths",
      "-ftrapv",
      "-ftree-ccp",
      "-ftree-ch",
      "-ftree-copy-prop",
      "-ftree-dce",
      "-ftree-loop-optimize",
      "-ftree-loop-vectorize",
      "-ftree-pre",
      "-ftree-pta",
      "-ftree-slp-vectorize",
      "-ftree-sra",
      "-funroll-all-loops",
      "-funsafe-math-optimizations",
      "-funswitch-loops",
      "-fvar-tracking-assignments",
      "-fweb"
    ]
  },
  "HBRF": {
    "best_time": 0.002591848373413086,
    "total_evaluations": 170,
    "enabled_flags": [
      "-falign-functions",
      "-falign-jumps",
      "-falign-labels",
      "-falign-loops",
      "-fassociative-math",
      "-fbranch-probabilities",
      "-fcaller-saves",
      "-fcprop-registers",
      "-fcse-follow-jumps",
      "-fdefer-pop",
      "-fdelayed-branch",
      "-fdevirtualize",
      "-fdse",
      "-fearly-inlining",
      "-fexceptions",
      "-ffast-math",
      "-fipa-cp",
      "-fipa-icf",
      "-finline-functions",
      "-fipa-modref",
      "-fipa-pure-const",
      "-fipa-sra",
      "-flive-range-shrinkage",
      "-fmove-loop-invariants",
      "-fomit-frame-pointer",
      "-foptimize-sibling-calls",
      "-fpeel-loops",
      "-fsched-interblock",
      "-fsection-anchors",
      "-fshort-enums",
      "-fshrink-wrap",
      "-fsplit-paths",
      "-fsplit-wide-types",
      "-fstrict-aliasing",
      "-ftrapv",
      "-ftree-builtin-call-dce",
      "-ftree-copy-prop",
      "-ftree-dce",
      "-ftree-dominator-opts",
      "-ftree-dse",
      "-ftree-forwprop",
      "-ftree-loop-optimize",
      "-ftree-pta",
      "-ftree-reassoc",
      "-ftree-sra",
      "-ftree-ter",
      "-funroll-all-loops",
      "-funswitch-loops",
      "-funwind-tables",
      "-fvar-tracking-assignments"
    ]
  },
  "XGBOOST": {
    "best_time": 0.002666950225830078,
    "total_evaluations": 100,
    "enabled_flags": [
      "-falign-functions",
      "-falign-jumps",
      "-falign-labels",
      "-falign-loops",
      "-fassociative-math",
      "-fauto-inc-dec",
      "-fbranch-probabilities",
      "-fcaller-saves",
      "-fcode-hoisting",
      "-fcombine-stack-adjustments",
      "-fconserve-stack",
      "-fcprop-registers",
      "-fcx-limited-range",
      "-fdce",
      "-fdefer-pop",
      "-fdelayed-branch",
      "-fdelete-null-pointer-checks",
      "-fdevirtualize",
      "-fdse",
      "-fearly-inlining",
      "-fexceptions",
      "-ffast-math",
      "-ffinite-math-only",
      "-fipa-cp-clone",
      "-fipa-pure-const",
      "-fipa-sra",
      "-fjump-tables",
      "-fomit-frame-pointer",
      "-frename-registers",
      "-frerun-cse-after-loop",
      "-fsection-anchors",
      "-fsplit-paths",
      "-ftree-builtin-call-dce",
      "-ftree-ccp",
      "-ftree-dce",
      "-ftree-dominator-opts",
      "-ftree-forwprop",
      "-ftree-fre",
      "-ftree-loop-vectorize",
      "-ftree-pre",
      "-ftree-pta",
      "-ftree-reassoc",
      "-funroll-all-loops",
      "-funswitch-loops",
      "-funwind-tables",
      "-fvar-tracking-assignments"
    ]
  },
  "winner": "AutoFlag",
  "improvements": {
    "AutoFlag_vs_O3": 24.47355895411939,
    "HBRF_vs_O3": 23.38431179082388,
    "XGBOOST_vs_O3": 21.164282190429205
  }
}